prefect_streamline/__init__.py
prefect_streamline/cli.py
prefect_streamline/core/__init__.py
prefect_streamline/core/deploy.py
prefect_streamline/core/importutils.py
prefect_streamline/core/waiting.py
prefect_streamline/deploybook.py
prefect_streamline/flowtest.py
prefect_streamline/py.typed
prefect_streamline-1.1.3.dist-info/LICENSE
prefect_streamline-1.1.3.dist-info/METADATA
prefect_streamline-1.1.3.dist-info/WHEEL
prefect_streamline-1.1.3.dist-info/entry_points.txt
prefect_streamline-1.1.3.dist-info/RECORD
