Metadata-Version: 2.1
Name: prefect-streamline
Version: 1.1.3
Summary: Prefect_Streamline is an opinionated extension that provides helpers to deploy and test Prefect flows quickly and easily.
License: MIT
Author: Fabien Arcellier
Author-email: fabien.arcellier@gmail.com
Requires-Python: >=3.8,<4.0
Classifier: Environment :: Console
Classifier: Intended Audience :: Developers
Classifier: License :: OSI Approved :: MIT License
Classifier: Operating System :: OS Independent
Classifier: Programming Language :: Python :: 3
Classifier: Programming Language :: Python :: 3.8
Classifier: Programming Language :: Python :: 3.9
Classifier: Programming Language :: Python :: 3.10
Classifier: Programming Language :: Python :: 3.11
Requires-Dist: click (>=8.1.3,<9.0.0)
Requires-Dist: prefect (>=2.8,<3.0)
Requires-Dist: requests (>=2.25.0,<3.0.0)
Requires-Dist: types-requests (>=2.25,<3.0)
